setup.py
jnltk/__init__.py
jnltk.egg-info/PKG-INFO
jnltk.egg-info/SOURCES.txt
jnltk.egg-info/dependency_links.txt
jnltk.egg-info/top_level.txt
jnltk/tokenize/__init__.py
jnltk/tokenize/simple.py
tests/__init__.py