Metadata-Version: 1.0
Name: jnltk
Version: 0.0.1
Summary: Japanese Natural Language Processing toolkit
Home-page: https://github.com/himkt/jnltk
Author: himkt
Author-email: himkt@klis.tsukuba.ac.jp
License: UNKNOWN
Platform: UNKNOWN
